AUTHORS
MANIFEST.in
README.md
README.rst
VERSION
setup.py
botscout/__init__.py
botscout/forms.py
botscout/settings.py
django_botscout.egg-info/PKG-INFO
django_botscout.egg-info/SOURCES.txt
django_botscout.egg-info/dependency_links.txt
django_botscout.egg-info/not-zip-safe
django_botscout.egg-info/top_level.txt