Metadata-Version: 1.1
Name: django-botscout
Version: 0.0.2
Summary: UNKNOWN
Home-page: http://labs.lyrical.net/lyrical/django-botscout
Author: Joey Wilhelm, Will LaShell
Author-email: tarkatronic@gmail.com, wlashell@lyrical.net
License: License :: OSI Approved
Platform: UNKNOWN
Classifier: Development Status :: 4 - Beta
Classifier: Environment :: Web Environment
Classifier: Intended Audience :: Developers
Classifier: License :: OSI Approved
Classifier: Operating System :: OS Independent
Classifier: Programming Language :: Python
Classifier: Framework :: Django
